testla/__init__.py
testla/cli.py
testla/pytest_plugin.py
testla/api/__init__.py
testla/domain/__init__.py
testla/domain/case.py
testla/domain/project.py
testla/domain/result.py
testla/domain/run.py
testla/repository/__init__.py
testla/repository/case_loader.py
testla/repository/config.py
testla/tui/__init__.py
testla/tui/app.py
testla/tui/styles.tcss
testla/tui/modals/__init__.py
testla/tui/modals/input.py
testla/tui/screens/__init__.py
testla/tui/screens/cases.py
testla/tui/screens/dashboard.py
testla/tui/widgets/__init__.py
testla/tui/widgets/nav.py
testla-0.1.1.dist-info/METADATA
testla-0.1.1.dist-info/WHEEL
testla-0.1.1.dist-info/entry_points.txt
testla-0.1.1.dist-info/licenses/LICENSE
testla-0.1.1.dist-info/RECORD
