Metadata-Version: 2.4
Name: testla
Version: 0.1.1
Summary: Git-native test case management
Author-email: m1yag1 <8730430+m1yag1@users.noreply.github.com>
License: Apache-2.0
License-File: LICENSE
Requires-Python: >=3.12
Requires-Dist: python-frontmatter>=1.1.0
Requires-Dist: pyyaml>=6.0.0
Requires-Dist: rich>=13.0.0
Requires-Dist: textual>=0.50.0
Requires-Dist: typer>=0.12.0
